nuitka_simple_gui.py
nuitka_simple_gui-2026.1.31.dist-info/entry_points.txt
nuitka_simple_gui-2026.1.31.dist-info/licenses/LICENSE
nuitka_simple_gui-2026.1.31.dist-info/WHEEL
nuitka_simple_gui-2026.1.31.dist-info/METADATA
nuitka_simple_gui-2026.1.31.dist-info/RECORD
