Metadata-Version: 2.4
Name: nuitka_simple_gui
Version: 2026.1.31
Summary: A simple GUI application using Nuitka.
Author-email: ClericPy <clericpy@gmail.com>
Classifier: License :: OSI Approved :: MIT License
License-File: LICENSE
Requires-Dist: FreeSimpleGUI
Requires-Dist: nuitka
Requires-Dist: pip
Project-URL: Home, https://github.com/ClericPy/nuitka_simple_gui
